DISTS_pytorch/DISTS_pt.py
DISTS_pytorch/__init__.py
DISTS_pytorch/weights.pt
DISTS_pytorch-0.1.data/data/weights.pt
DISTS_pytorch-0.1.dist-info/LICENSE
DISTS_pytorch-0.1.dist-info/METADATA
DISTS_pytorch-0.1.dist-info/WHEEL
DISTS_pytorch-0.1.dist-info/top_level.txt
DISTS_pytorch-0.1.dist-info/RECORD
