Metadata-Version: 2.1
Name: DISTS-pytorch
Version: 0.1
Summary: Deep Image Structure and Texture Similarity (DISTS) Metric
Home-page: https://github.com/dingkeyan93/DISTS
Author: Keyan Ding
Author-email: dingkeyan93@outlook.com
License: MIT
Keywords: pytorch,similarity,VGG,texture,structure,metric
Platform: python
Requires-Dist: torch (>=1.0)
